Workbook
Name Total_Net_Sales_C: Income_Statement!$C$17

Sheet ReadMe
B1: Apple_Retail_FPA_Model.xlsx — Methodology & ReadMe
B3: PURPOSE
B4: Portfolio-style FP&A model built on Apple Inc.'s actual FY2024–FY2025 financial statements, extended into a 3-statement projection (FY2026E–FY2028E) with a dedicated Retail Net Sales driver structure. This is Phase 1–2 of a 5-phase build (Foundation + Core 3-Statement Model); CapEx/Headcount schedules, BvA automation, and the executive dashboard/portfolio package come in later phases.
B6: TAB GUIDE
B7: • Assumptions — every driver used by the model (revenue growth, margins, working-capital days, CapEx/D&A, capital return). Blue = input; a comment on each cell states whether it's an ACTUAL 10-K figure or an analyst ESTIMATE, with the source.
B8: • Income_Statement — builds Total Net Sales from a Retail (Stores + E-Commerce) and Indirect/Wholesale channel structure, then flows through COGS, opex, taxes to Net Income and diluted EPS.
B9: • Balance_Sheet — links working-capital lines to Income Statement drivers (days outstanding), rolls PP&E forward with CapEx and D&A from the Cash Flow tab, and rolls equity forward with Net Income, dividends, buybacks, and stock-based comp. Row 41 is a Balance Check that must equal zero.
B10: • Cash_Flow — indirect-method statement; operating section is driven by Net Income (from the Income Statement) plus the period-over-period change in each Balance Sheet working-capital line. Ending cash links back into the Balance Sheet's Cash line, closing the loop.
B12: KEY ASSUMPTION TO FLAG IN AN INTERVIEW
B13: Apple's 10-K does not disclose a Retail Stores vs. E-Commerce net sales split, or a store/online split of the year-by-year Direct-vs-Indirect distribution channel mix. It discloses only: (1) net sales by product/service category, (2) net sales by geographic segment, and (3) a single-year FY2025 statement that Direct channels (retail + online stores + direct sales force) were 40% of total net sales and Indirect channels (carriers/resellers) were 60%. This model treats that 40% as the Direct/Retail base, splits it 55% Stores / 45% E-Commerce as a labeled analyst estimate, and grows the three channels (Stores, E-Commerce, Indirect) independently for FY2026E–FY2028E — which is what actually 'drives' Total Net Sales in the projection years, per the project brief. Every estimated cell carries a comment explaining this.
B15: SIMPLIFICATIONS (documented, not hidden)
B16: • No revolver/interest circularity — Other Income/(Expense) is held as a flat % of sales rather than computed off the cash balance, so the model has no circular references.
... B22: Apple Inc. Form 10-K for fiscal year ended September 27, 2025 (SEC EDGAR, filed October 2025); Apple Inc. Q4 FY2025 Condensed Consolidated Financial Statements (apple.com/newsroom, October 30, 2025).

Sheet Dashboard
B2: Apple Retail FP&A — Executive Dashboard
B3: FY2025A actuals vs. FY2026E–FY2028E projections. Source: Income_Statement, Balance_Sheet, Retail_CapEx, GRS_Headcount tabs.
B5: FY2025A Net Sales | D5: FY2028E Net Sales | F5: FY2025A Net Margin | H5: FY2028E Net Margin
B6: =Income_Statement!C17 -> 416161 | D6: =Income_Statement!F17 -> 496473.51 | F6: =Income_Statement!C39 -> 0.26915064 | H6: =Income_Statement!F39 -> 0.2856
B7: Actual, 10-K | D7: Projected | F7: Actual | H7: Projected
B9: FY2025A Retail CapEx | D9: FY2028E Retail CapEx | F9: FY2025A GRS Run Rate | H9: GRS Contractor Mix
B10: =Retail_CapEx!C21 -> 763 | D10: =Retail_CapEx!F21 -> 914.00299 | F10: =GRS_Headcount!C19 -> 683.3 | H10: =GRS_Headcount!C10 -> 0.23684211
B11: Estimate, see ReadMe | D11: Projected | F11: Illustrative | H11: FY2025, illustrative
B13: CHART DATA (feeds charts below — linked, not hardcoded)
B14: Year | C14: =Income_Statement!B4 -> FY2024A | D14: =Income_Statement!C4 -> FY2025A | E14: =Income_Statement!D4 -> FY2026E | F14: =Income_Statement!E4 -> FY2027E | G14: =Income_Statement!F4 -> FY2028E
B15: Total Net Sales ($M) | C15: =Income_Statement!B17 -> 391035 | D15: =Income_Statement!C17 -> 416161 | E15: =Income_Statement!D17 -> 442295.91 | F15: =Income_Statement!E17 -> 469401.31 | G15: =Income_Statement!F17 -> 496473.51
B16: Net Margin % | C16: =Income_Statement!B39 -> 0.23971256 | D16: =Income_Statement!C39 -> 0.26915064 | E16: =Income_Statement!D39 -> 0.27468 | F16: =Income_Statement!E39 -> 0.27972 | G16: =Income_Statement!F39 -> 0.2856
B18: Retail CapEx by Category ($M)
C19: =Income_Statement!B4 -> FY2024A | D19: =Income_Statement!C4 -> FY2025A | E19: =Income_Statement!D4 -> FY2026E | F19: =Income_Statement!E4 -> FY2027E | G19: =Income_Statement!F4 -> FY2028E
B20: New Store Buildouts | C20: =Retail_CapEx!B9 -> 142 | D20: =Retail_CapEx!C9 -> 191 | E20: =Retail_CapEx!D9 -> 192 | F20: =Retail_CapEx!E9 -> 212.5 | G20: =Retail_CapEx!F9 -> 234
B21: Store Remodels | C21: =Retail_CapEx!B14 -> 255 | D21: =Retail_CapEx!C14 -> 343 | E21: =Retail_CapEx!D14 -> 345 | F21: =Retail_CapEx!E14 -> 369.2 | G21: =Retail_CapEx!F14 -> 394.2
B22: Retail IT | C22: =Retail_CapEx!B18 -> 170 | D22: =Retail_CapEx!C18 -> 229 | E22: =Retail_CapEx!D18 -> 247.32 | F22: =Retail_CapEx!E18 -> 267.1056 | G22: =Retail_CapEx!F18 -> 285.80299
B24: GRS Headcount Mix
C25: =Income_Statement!B4 -> FY2024A | D25: =Income_Statement!C4 -> FY2025A | E25: =Income_Statement!D4 -> FY2026E | F25: =Income_Statement!E4 -> FY2027E | G25: =Income_Statement!F4 -> FY2028E
B26: Corporate FTEs | C26: =GRS_Headcount!B7 -> 2750 | D26: =GRS_Headcount!C7 -> 2900 | E26: =GRS_Headcount!D7 -> 3050 | F26: =GRS_Headcount!E7 -> 3150 | G26: =GRS_Headcount!F7 -> 3250
B27: External Contractors | C27: =GRS_Headcount!B8 -> 820 | D27: =GRS_Headcount!C8 -> 900 | E27: =GRS_Headcount!D8 -> 950 | F27: =GRS_Headcount!E8 -> 970 | G27: =GRS_Headcount!F8 -> 980

Sheet Assumptions
A1: Apple Inc. — Retail FP&A Model: Key Assumptions & Drivers
A2: Historical figures (FY2024A–FY2025A) are sourced from Apple's FY2025 Form 10-K and Q4 FY2025 earnings release. Projection-year (FY2026E–FY2028E) inputs are analyst assumptions, shown in blue.
A4: ($ in millions, except per-share and days figures) | B4: FY2024A | C4: FY2025A | D4: FY2026E | E4: FY2027E | F4: FY2028E
A6: REVENUE DRIVERS — RETAIL/CHANNEL BUILD
A8: Retail Net Sales – Stores: YoY Growth % | D8: 0.04 | E8: 0.04 | F8: 0.045
A9: Retail Net Sales – E-Commerce: YoY Growth % | D9: 0.1 | E9: 0.09 | F9: 0.08
A10: Indirect / Wholesale Channel: YoY Growth % | D10: 0.06 | E10: 0.06 | F10: 0.055
A11: Retail Stores as % of Direct (Retail) Channel | C11: 0.55 | D11: =C11 -> 0.55 | E11: =C11 -> 0.55 | F11: =C11 -> 0.55
A12: Direct (Retail) Channel as % of Total Net Sales | C12: 0.4
A14: MARGIN & COST DRIVERS
A16: Blended Gross Margin % | C16: 0.469 | D16: 0.473 | E16: 0.478 | F16: 0.482
A17: R&D as % of Net Sales | C17: 0.083 | D17: 0.08 | E17: 0.08 | F17: 0.078
A18: SG&A as % of Net Sales | C18: 0.0663 | D18: 0.066 | E18: 0.065 | F18: 0.064
A19: Effective Tax Rate | C19: 0.156 | D19: 0.16 | E19: 0.16 | F19: 0.16
A20: Other Income/(Expense), net, as % of Net Sales | D20: 0 | E20: 0 | F20: 0
A22: BALANCE SHEET DRIVERS
A24: Accounts Receivable Days (Net Sales basis) | C24: 34.9 | D24: =C24 -> 34.9 | E24: =D24 -> 34.9 | F24: =E24 -> 34.9
A25: Inventory Days (COGS basis) | C25: 9.4 | D25: =C25 -> 9.4 | E25: =D25 -> 9.4 | F25: =E25 -> 9.4
A26: Accounts Payable Days (COGS basis) | C26: 115.4 | D26: =C26 -> 115.4 | E26: =D26 -> 115.4 | F26: =E26 -> 115.4
A27: Vendor Non-Trade Receivables, % of Net Sales | C27: 0.0797 | D27: =C27 -> 0.0797 | E27: =D27 -> 0.0797 | F27: =E27 -> 0.0797
A28: Other Current Assets, % of Net Sales | C28: 0.035 | D28: =C28 -> 0.035 | E28: =D28 -> 0.035 | F28: =E28 -> 0.035
A29: Other Non-Current Assets, % of Net Sales | C29: 0.2012 | D29: =C29 -> 0.2012 | E29: =D29 -> 0.2012 | F29: =E29 -> 0.2012
A30: Marketable Securities – Current ($M, held flat) | C30: 18763 | D30: =C30 -> 18763 | E30: =D30 -> 18763 | F30: =E30 -> 18763
A31: Marketable Securities – Non-Current ($M, held flat) | C31: 77723 | D31: =C31 -> 77723 | E31: =D31 -> 77723 | F31: =E31 -> 77723
A32: Other Current Liabilities, % of Net Sales | C32: 0.1595 | D32: =C32 -> 0.1595 | E32: =D32 -> 0.1595 | F32: =E32 -> 0.1595
A33: Deferred Revenue, % of Net Sales | C33: 0.0218 | D33: =C33 -> 0.0218 | E33: =D33 -> 0.0218 | F33: =E33 -> 0.0218
A34: Other Non-Current Liabilities, % of Net Sales | C34: 0.0998 | D34: =C34 -> 0.0998 | E34: =D34 -> 0.0998 | F34: =E34 -> 0.0998
A35: Commercial Paper ($M, held flat) | C35: 7979 | D35: =C35 -> 7979 | E35: =D35 -> 7979 | F35: =E35 -> 7979
... A38: Accumulated Other Comprehensive Income/(Loss) ($M, held flat) | C38: -5571 | D38: =C38 -> -5571 | E38: =D38 -> -5571 | F38: =E38 -> -5571
A40: CASH FLOW / CAPITAL RETURN DRIVERS
A42: Other (Non-Retail) CapEx as % of Net Sales | C42: =(12715-Retail_CapEx!C$21)/Income_Statement!C$17 -> 0.028719654 | D42: 0.026 | E42: 0.026 | F42: 0.025
A43: Other (Non-Retail) D&A as % of Net Sales | C43: =(11698-Retail_CapEx!C$35)/Income_Statement!C$17 -> 0.027105663 | D43: 0.023 | E43: 0.023 | F43: 0.022
A44: Stock-Based Compensation as % of Net Sales | C44: 0.0309 | D44: =C44 -> 0.0309 | E44: =D44 -> 0.0309 | F44: =E44 -> 0.0309
A45: Dividend $ Growth Rate, YoY | D45: 0.03 | E45: 0.03 | F45: 0.03
A46: Share Repurchases ($M per year) | D46: 88000 | E46: 85000 | F46: 82000
A47: Diluted Share Count Growth Rate (buyback effect) | D47: -0.02 | E47: -0.02 | F47: -0.018

Sheet Income_Statement
A1: Apple Inc. — Consolidated Income Statement (Retail-Driven Build)
A2: FY2024A–FY2025A actuals: Apple FY2025 Form 10-K, Consolidated Statements of Operations. FY2026E–FY2028E: projected off Assumptions tab drivers.
A4: ($ in millions, except per-share and days figures) | B4: FY2024A | C4: FY2025A | D4: FY2026E | E4: FY2027E | F4: FY2028E
A6: RETAIL / CHANNEL NET SALES BUILD (modeled — drives Total Net Sales)
A7: Retail Net Sales – Stores | B7: n/d | C7: =Total_Net_Sales_C*Assumptions!$C$12*Assumptions!$C$11 -> 91555.42 | D7: =C7*(1+Assumptions!D8) -> 95217.637 | E7: =D7*(1+Assumptions!E8) -> 99026.342 | F7: =E7*(1+Assumptions!F8) -> 103482.53
A8: Retail Net Sales – E-Commerce | B8: n/d | C8: =Total_Net_Sales_C*Assumptions!$C$12*(1-Assumptions!$C$11) -> 74908.98 | D8: =C8*(1+Assumptions!D9) -> 82399.878 | E8: =D8*(1+Assumptions!E9) -> 89815.867 | F8: =E8*(1+Assumptions!F9) -> 97001.136
A9: Total Retail (Direct) Net Sales | B9: n/d | C9: =C7+C8 -> 166464.4 | D9: =D7+D8 -> 177617.51 | E9: =E7+E8 -> 188842.21 | F9: =F7+F8 -> 200483.66
A10: Indirect / Wholesale Channel Net Sales | B10: n/d | C10: =Total_Net_Sales_C-C9 -> 249696.6 | D10: =C10*(1+Assumptions!D10) -> 264678.4 | E10: =D10*(1+Assumptions!E10) -> 280559.1 | F10: =E10*(1+Assumptions!F10) -> 295989.85
A12: MEMO: NET SALES BY PRODUCT/SERVICE CATEGORY (as reported)
A13: Products | B13: 294866 | C13: 307003 | D13: =D$17*($C13/Total_Net_Sales_C) -> 326282.79 | E13: =E$17*($C13/Total_Net_Sales_C) -> 346278.51 | F13: =F$17*($C13/Total_Net_Sales_C) -> 366249.74
A14: Services | B14: 96169 | C14: 109158 | D14: =D$17-D13 -> 116013.12 | E14: =E$17-E13 -> 123122.8 | F14: =F$17-F13 -> 130223.77
A16: TOTAL NET SALES
A17: Total Net Sales | B17: 391035 | C17: 416161 | D17: =D9+D10 -> 442295.91 | E17: =E9+E10 -> 469401.31 | F17: =F9+F10 -> 496473.51
A18: YoY Growth % | C18: =C17/B17-1 -> 0.064255118 | D18: =D17/C17-1 -> 0.0628 | E18: =E17/D17-1 -> 0.061283402 | F18: =F17/E17-1 -> 0.057673902
A20: COST OF SALES & GROSS MARGIN
A21: Products Cost of Sales (memo) | B21: 185233 | C21: 194116 | D21: see blended COGS below
A22: Services Cost of Sales (memo) | B22: 25119 | C22: 26844
A23: Total Cost of Sales | B23: 210352 | C23: 220960 | D23: =D17*(1-Assumptions!D$16) -> 233089.94 | E23: =E17*(1-Assumptions!E$16) -> 245027.48 | F23: =F17*(1-Assumptions!F$16) -> 257173.28
A24: Gross Margin | B24: =B17-B23 -> 180683 | C24: =C17-C23 -> 195201 | D24: =D17-D23 -> 209205.97 | E24: =E17-E23 -> 224373.83 | F24: =F17-F23 -> 239300.23
A25: Gross Margin % | B25: =B24/B17 -> 0.4620635 | C25: =C24/C17 -> 0.46905164 | D25: =D24/D17 -> 0.473 | E25: =E24/E17 -> 0.478 | F25: =F24/F17 -> 0.482
A27: OPERATING EXPENSES
A28: Research & Development | B28: 31370 | C28: 34550 | D28: =D17*Assumptions!D$17 -> 35383.673 | E28: =E17*Assumptions!E$17 -> 37552.105 | F28: =F17*Assumptions!F$17 -> 38724.934
A29: Selling, General & Administrative | B29: 26097 | C29: 27601 | D29: =D17*Assumptions!D$18 -> 29191.53 | E29: =E17*Assumptions!E$18 -> 30511.085 | F29: =F17*Assumptions!F$18 -> 31774.305
A30: Total Operating Expenses | B30: =B28+B29 -> 57467 | C30: =C28+C29 -> 62151 | D30: =D28+D29 -> 64575.203 | E30: =E28+E29 -> 68063.19 | F30: =F28+F29 -> 70499.239
A31: Operating Income | B31: =B24-B30 -> 123216 | C31: =C24-C30 -> 133050 | D31: =D24-D30 -> 144630.76 | E31: =E24-E30 -> 156310.64 | F31: =F24-F30 -> 168800.99
A32: Operating Margin % | B32: =B31/B17 -> 0.31510223 | C32: =C31/C17 -> 0.319708 | D32: =D31/D17 -> 0.327 | E32: =E31/E17 -> 0.333 | F32: =F31/F17 -> 0.34
A34: NET INCOME
A35: Other Income/(Expense), net | B35: 269 | C35: -321 | D35: =D17*Assumptions!D$20 -> 0 | E35: =E17*Assumptions!E$20 -> 0 | F35: =F17*Assumptions!F$20 -> 0
A36: Income Before Provision for Income Taxes | B36: =B31+B35 -> 123485 | C36: =C31+C35 -> 132729 | D36: =D31+D35 -> 144630.76 | E36: =E31+E35 -> 156310.64 | F36: =F31+F35 -> 168800.99
A37: Provision for Income Taxes | B37: 29749 | C37: 20719 | D37: =D36*Assumptions!D$19 -> 23140.922 | E37: =E36*Assumptions!E$19 -> 25009.702 | F37: =F36*Assumptions!F$19 -> 27008.159
A38: Net Income | B38: =B36-B37 -> 93736 | C38: =C36-C37 -> 112010 | D38: =D36-D37 -> 121489.84 | E38: =E36-E37 -> 131300.93 | F38: =F36-F37 -> 141792.84
A39: Net Margin % | B39: =B38/B17 -> 0.23971256 | C39: =C38/C17 -> 0.26915064 | D39: =D38/D17 -> 0.27468 | E39: =E38/E17 -> 0.27972 | F39: =F38/F17 -> 0.2856
A41: PER-SHARE DATA
A42: Diluted Shares Outstanding (000s) | B42: 15408095 | C42: 15004697 | D42: =C42*(1+Assumptions!D$47) -> 14704603 | E42: =D42*(1+Assumptions!E$47) -> 14410511 | F42: =E42*(1+Assumptions!F$47) -> 14151122
A43: Diluted EPS | B43: =B38*1000/B42 -> 6.0835554 | C43: =C38*1000/C42 -> 7.4649958 | D43: =D38*1000/D42 -> 8.2620279 | E43: =E38*1000/E42 -> 9.1114697 | F43: =F38*1000/F42 -> 10.019901

Sheet Balance_Sheet
A1: Apple Inc. — Consolidated Balance Sheet
A2: FY2024A–FY2025A actuals: Apple FY2025 10-K / Q4 FY2025 earnings release, Condensed Consolidated Balance Sheets. FY2026E–FY2028E: linked to Income Statement & Cash Flow drivers.
A4: ($ in millions, except per-share and days figures) | B4: FY2024A | C4: FY2025A | D4: FY2026E | E4: FY2027E | F4: FY2028E
A6: ASSETS
A7: Cash and Cash Equivalents | B7: =Cash_Flow!B$35 -> 29943 | C7: =Cash_Flow!C$35 -> 35934 | D7: =Cash_Flow!D$35 -> 59757.83 | E7: =Cash_Flow!E$35 -> 96458.805 | F7: =Cash_Flow!F$35 -> 146987.23
A8: Marketable Securities – Current | B8: 35228 | C8: 18763 | D8: =Assumptions!D$30 -> 18763 | E8: =Assumptions!E$30 -> 18763 | F8: =Assumptions!F$30 -> 18763
A9: Accounts Receivable, net | B9: 33410 | C9: 39777 | D9: =Income_Statement!D$17/365*Assumptions!D$24 -> 42290.76 | E9: =Income_Statement!E$17/365*Assumptions!E$24 -> 44882.481 | F9: =Income_Statement!F$17/365*Assumptions!F$24 -> 47471.029
A10: Vendor Non-Trade Receivables | B10: 32833 | C10: 33180 | D10: =Income_Statement!D$17*Assumptions!D$27 -> 35250.984 | E10: =Income_Statement!E$17*Assumptions!E$27 -> 37411.284 | F10: =Income_Statement!F$17*Assumptions!F$27 -> 39568.939
A11: Inventories | B11: 7286 | C11: 5718 | D11: =Income_Statement!D$23/365*Assumptions!D$25 -> 6002.8643 | E11: =Income_Statement!E$23/365*Assumptions!E$25 -> 6310.2968 | F11: =Income_Statement!F$23/365*Assumptions!F$25 -> 6623.0927
A12: Other Current Assets | B12: 14287 | C12: 14585 | D12: =Income_Statement!D$17*Assumptions!D$28 -> 15480.357 | E12: =Income_Statement!E$17*Assumptions!E$28 -> 16429.046 | F12: =Income_Statement!F$17*Assumptions!F$28 -> 17376.573
A13: Total Current Assets | B13: =SUM(B7:B12) -> 152987 | C13: =SUM(C7:C12) -> 147957 | D13: =SUM(D7:D12) -> 177545.8 | E13: =SUM(E7:E12) -> 220254.91 | F13: =SUM(F7:F12) -> 276789.87
A15: Marketable Securities – Non-Current | B15: 91479 | C15: 77723 | D15: =Assumptions!D$31 -> 77723 | E15: =Assumptions!E$31 -> 77723 | F15: =Assumptions!F$31 -> 77723
A16: Property, Plant & Equipment, net | B16: 45680 | C16: 49834 | D16: =C16-Cash_Flow!D$20-Cash_Flow!D$8 -> 51468.541 | E16: =D16-Cash_Flow!E$20-Cash_Flow!E$8 -> 53184.664 | F16: =E16-Cash_Flow!F$20-Cash_Flow!F$8 -> 54975.771
A17: Other Non-Current Assets | B17: 74834 | C17: 83727 | D17: =Income_Statement!D$17*Assumptions!D$29 -> 88989.937 | E17: =Income_Statement!E$17*Assumptions!E$29 -> 94443.543 | F17: =Income_Statement!F$17*Assumptions!F$29 -> 99890.471
A18: Total Non-Current Assets | B18: =SUM(B15:B17) -> 211993 | C18: =SUM(C15:C17) -> 211284 | D18: =SUM(D15:D17) -> 218181.48 | E18: =SUM(E15:E17) -> 225351.21 | F18: =SUM(F15:F17) -> 232589.24
A19: TOTAL ASSETS | B19: =B13+B18 -> 364980 | C19: =C13+C18 -> 359241 | D19: =D13+D18 -> 395727.27 | E19: =E13+E18 -> 445606.12 | F19: =F13+F18 -> 509379.11
A21: LIABILITIES
A22: Accounts Payable | B22: 68960 | C22: 69860 | D22: =Income_Statement!D$23/365*Assumptions!D$26 -> 73694.739 | E22: =Income_Statement!E$23/365*Assumptions!E$26 -> 77468.963 | F22: =Income_Statement!F$23/365*Assumptions!F$26 -> 81309.032
A23: Other Current Liabilities | B23: 78304 | C23: 66387 | D23: =Income_Statement!D$17*Assumptions!D$32 -> 70546.198 | E23: =Income_Statement!E$17*Assumptions!E$32 -> 74869.509 | F23: =Income_Statement!F$17*Assumptions!F$32 -> 79187.526
A24: Deferred Revenue | B24: 8249 | C24: 9055 | D24: =Income_Statement!D$17*Assumptions!D$33 -> 9642.0509 | E24: =Income_Statement!E$17*Assumptions!E$33 -> 10232.949 | F24: =Income_Statement!F$17*Assumptions!F$33 -> 10823.123
A25: Commercial Paper | B25: 9967 | C25: 7979 | D25: =Assumptions!D$35 -> 7979 | E25: =Assumptions!E$35 -> 7979 | F25: =Assumptions!F$35 -> 7979
A26: Term Debt – Current | B26: 10912 | C26: 12350 | D26: =Assumptions!D$36 -> 12350 | E26: =Assumptions!E$36 -> 12350 | F26: =Assumptions!F$36 -> 12350
A27: Total Current Liabilities | B27: =SUM(B22:B26) -> 176392 | C27: =SUM(C22:C26) -> 165631 | D27: =SUM(D22:D26) -> 174211.99 | E27: =SUM(E22:E26) -> 182900.42 | F27: =SUM(F22:F26) -> 191648.68
A29: Term Debt – Non-Current | B29: 85750 | C29: 78328 | D29: =Assumptions!D$37 -> 78328 | E29: =Assumptions!E$37 -> 78328 | F29: =Assumptions!F$37 -> 78328
A30: Other Non-Current Liabilities | B30: 45888 | C30: 41549 | D30: =Income_Statement!D$17*Assumptions!D$34 -> 44141.132 | E30: =Income_Statement!E$17*Assumptions!E$34 -> 46846.251 | F30: =Income_Statement!F$17*Assumptions!F$34 -> 49548.057
A31: Total Non-Current Liabilities | B31: =SUM(B29:B30) -> 131638 | C31: =SUM(C29:C30) -> 119877 | D31: =SUM(D29:D30) -> 122469.13 | E31: =SUM(E29:E30) -> 125174.25 | F31: =SUM(F29:F30) -> 127876.06
A32: TOTAL LIABILITIES | B32: =B27+B31 -> 308030 | C32: =C27+C31 -> 285508 | D32: =D27+D31 -> 296681.12 | E32: =E27+E31 -> 308074.67 | F32: =F27+F31 -> 319524.74
A34: SHAREHOLDERS' EQUITY
A35: Common Stock & Additional Paid-In Capital | B35: 83276 | C35: 93568 | D35: =C35+Cash_Flow!D$9 -> 107234.94 | E35: =D35+Cash_Flow!E$9 -> 121739.44 | F35: =E35+Cash_Flow!F$9 -> 137080.48
A36: Accumulated Deficit / Retained Earnings | B36: -19154 | C36: -14264 | D36: =C36+Income_Statement!D$38+Cash_Flow!D$26+Cash_Flow!D$27+Cash_Flow!D$25 -> -2617.7892 | E36: =D36+Income_Statement!E$38+Cash_Flow!E$26+Cash_Flow!E$27+Cash_Flow!E$25 -> 21363.006 | F36: =E36+Income_Statement!F$38+Cash_Flow!F$26+Cash_Flow!F$27+Cash_Flow!F$25 -> 58344.899
A37: Accumulated Other Comprehensive Income/(Loss) | B37: -7172 | C37: -5571 | D37: =Assumptions!D$38 -> -5571 | E37: =Assumptions!E$38 -> -5571 | F37: =Assumptions!F$38 -> -5571
A38: Total Shareholders' Equity | B38: =SUM(B35:B37) -> 56950 | C38: =SUM(C35:C37) -> 73733 | D38: =SUM(D35:D37) -> 99046.154 | E38: =SUM(E35:E37) -> 137531.45 | F38: =SUM(F35:F37) -> 189854.37
A39: TOTAL LIABILITIES AND SHAREHOLDERS' EQUITY | B39: =B32+B38 -> 364980 | C39: =C32+C38 -> 359241 | D39: =D32+D38 -> 395727.27 | E39: =E32+E38 -> 445606.12 | F39: =F32+F38 -> 509379.11
A41: Balance Check (Assets − Liabilities & Equity; must = 0) | B41: =B19-B39 -> 0 | C41: =C19-C39 -> 0 | D41: =D19-D39 -> 0 | E41: =E19-E39 -> 0 | F41: =F19-F39 -> 0

Sheet Cash_Flow
A1: Apple Inc. — Consolidated Statement of Cash Flows
A2: FY2024A–FY2025A actuals: Apple Q4 FY2025 earnings release, Condensed Consolidated Statements of Cash Flows. FY2026E–FY2028E: derived from Income Statement & Balance Sheet changes (indirect method).
A4: ($ in millions, except per-share and days figures) | B4: FY2024A | C4: FY2025A | D4: FY2026E | E4: FY2027E | F4: FY2028E
A6: OPERATING ACTIVITIES
A7: Net Income | B7: =Income_Statement!B$38 -> 93736 | C7: =Income_Statement!C$38 -> 112010 | D7: =Income_Statement!D$38 -> 121489.84 | E7: =Income_Statement!E$38 -> 131300.93 | F7: =Income_Statement!F$38 -> 141792.84
A8: Depreciation & Amortization | B8: 11445 | C8: 11698 | D8: =Retail_CapEx!D$35+Income_Statement!D$17*Assumptions!D$43 -> 10649.473 | E8: =Retail_CapEx!E$35+Income_Statement!E$17*Assumptions!E$43 -> 11337.116 | F8: =Retail_CapEx!F$35+Income_Statement!F$17*Assumptions!F$43 -> 11534.734
A9: Stock-Based Compensation Expense | B9: 11688 | C9: 12863 | D9: =Income_Statement!D$17*Assumptions!D$44 -> 13666.944 | E9: =Income_Statement!E$17*Assumptions!E$44 -> 14504.5 | F9: =Income_Statement!F$17*Assumptions!F$44 -> 15341.032
A10: Other Operating Adjustments | B10: -2266 | C10: -89 | D10: 0 | E10: 0 | F10: 0
A11: Δ Accounts Receivable, net | B11: -3788 | C11: -6682 | D11: =-(Balance_Sheet!D$9-Balance_Sheet!C$9) -> -2513.7597 | E11: =-(Balance_Sheet!E$9-Balance_Sheet!D$9) -> -2591.7216 | F11: =-(Balance_Sheet!F$9-Balance_Sheet!E$9) -> -2588.5478
A12: Δ Vendor Non-Trade Receivables | B12: -1356 | C12: -347 | D12: =-(Balance_Sheet!D$10-Balance_Sheet!C$10) -> -2070.9841 | E12: =-(Balance_Sheet!E$10-Balance_Sheet!D$10) -> -2160.3002 | F12: =-(Balance_Sheet!F$10-Balance_Sheet!E$10) -> -2157.6548
A13: Δ Inventories | B13: -1046 | C13: 1400 | D13: =-(Balance_Sheet!D$11-Balance_Sheet!C$11) -> -284.86434 | E13: =-(Balance_Sheet!E$11-Balance_Sheet!D$11) -> -307.43249 | F13: =-(Balance_Sheet!F$11-Balance_Sheet!E$11) -> -312.79587
A14: Δ Other Current & Non-Current Assets | B14: -11731 | C14: -9197 | D14: =-((Balance_Sheet!D$12+Balance_Sheet!D$17)-(Balance_Sheet!C$12+Balance_Sheet!C$17)) -> -6158.2941 | E14: =-((Balance_Sheet!E$12+Balance_Sheet!E$17)-(Balance_Sheet!D$12+Balance_Sheet!D$17)) -> -6402.2951 | F14: =-((Balance_Sheet!F$12+Balance_Sheet!F$17)-(Balance_Sheet!E$12+Balance_Sheet!E$17)) -> -6394.4549
A15: Δ Accounts Payable | B15: 6020 | C15: 902 | D15: =(Balance_Sheet!D$22-Balance_Sheet!C$22) -> 3834.7388 | E15: =(Balance_Sheet!E$22-Balance_Sheet!D$22) -> 3774.2244 | F15: =(Balance_Sheet!F$22-Balance_Sheet!E$22) -> 3840.0684
A16: Δ Other Current & Non-Current Liabilities | B16: 15552 | C16: -11076 | D16: =((Balance_Sheet!D$23+Balance_Sheet!D$24+Balance_Sheet!D$30)-(Balance_Sheet!C$23+Balance_Sheet!C$24+Balance_Sheet!C$30)) -> 7338.3805 | E16: =((Balance_Sheet!E$23+Balance_Sheet!E$24+Balance_Sheet!E$30)-(Balance_Sheet!D$23+Balance_Sheet!D$24+Balance_Sheet!D$30)) -> 7619.3274 | F16: =((Balance_Sheet!F$23+Balance_Sheet!F$24+Balance_Sheet!F$30)-(Balance_Sheet!E$23+Balance_Sheet!E$24+Balance_Sheet!E$30)) -> 7609.9969
A17: Cash Generated by Operating Activities | B17: =SUM(B7:B16) -> 118254 | C17: =SUM(C7:C16) -> 111482 | D17: =SUM(D7:D16) -> 145951.47 | E17: =SUM(E7:E16) -> 157074.35 | F17: =SUM(F7:F16) -> 168665.21
A19: INVESTING ACTIVITIES
A20: Payments for Acquisition of Property, Plant & Equipment (CapEx) | B20: -9447 | C20: -12715 | D20: =-(Retail_CapEx!D$21+Income_Statement!D$17*Assumptions!D$42) -> -12284.014 | E20: =-(Retail_CapEx!E$21+Income_Statement!E$17*Assumptions!E$42) -> -13053.24 | F20: =-(Retail_CapEx!F$21+Income_Statement!F$17*Assumptions!F$42) -> -13325.841
A21: Marketable Securities Activity & Other, net | B21: 12382 | C21: 27910 | D21: 0 | E21: 0 | F21: 0
A22: Cash Generated by/(Used in) Investing Activities | B22: =SUM(B20:B21) -> 2935 | C22: =SUM(C20:C21) -> 15195 | D22: =SUM(D20:D21) -> -12284.014 | E22: =SUM(E20:E21) -> -13053.24 | F22: =SUM(F20:F21) -> -13325.841
A24: FINANCING ACTIVITIES
A25: Taxes Paid for Net Share Settlement of Equity Awards | B25: -5441 | C25: -5960 | D25: =C25 -> -5960 | E25: =D25 -> -5960 | F25: =E25 -> -5960
A26: Dividends & Dividend Equivalents Paid | B26: -15234 | C26: -15421 | D26: =C26*(1+Assumptions!D$45) -> -15883.63 | E26: =D26*(1+Assumptions!E$45) -> -16360.139 | F26: =E26*(1+Assumptions!F$45) -> -16850.943
A27: Repurchases of Common Stock | B27: -94949 | C27: -90711 | D27: =-Assumptions!D$46 -> -88000 | E27: =-Assumptions!E$46 -> -85000 | F27: =-Assumptions!F$46 -> -82000
A28: Term Debt Issued/(Repaid), net | B28: -9958 | C28: -6451 | D28: 0 | E28: 0 | F28: 0
A29: Commercial Paper Issued/(Repaid), net | B29: 3960 | C29: -2032 | D29: 0 | E29: 0 | F29: 0
A30: Other Financing Activities | B30: -361 | C30: -111 | D30: 0 | E30: 0 | F30: 0
A31: Cash Used in Financing Activities | B31: =SUM(B25:B30) -> -121983 | C31: =SUM(C25:C30) -> -120686 | D31: =SUM(D25:D30) -> -109843.63 | E31: =SUM(E25:E30) -> -107320.14 | F31: =SUM(F25:F30) -> -104810.94
A33: Net Increase/(Decrease) in Cash | B33: =B17+B22+B31 -> -794 | C33: =C17+C22+C31 -> 5991 | D33: =D17+D22+D31 -> 23823.83 | E33: =E17+E22+E31 -> 36700.975 | F33: =F17+F22+F31 -> 50528.429
A34: Cash, Beginning of Period | B34: 30737 | C34: =B35 -> 29943 | D34: =C35 -> 35934 | E34: =D35 -> 59757.83 | F34: =E35 -> 96458.805
A35: Cash, End of Period | B35: =B33+B34 -> 29943 | C35: =C33+C34 -> 35934 | D35: =D33+D34 -> 59757.83 | E35: =E33+E34 -> 96458.805 | F35: =F33+F34 -> 146987.23

Sheet Retail_CapEx
A1: Apple Inc. — Retail CapEx & Depreciation Schedule
A2: ILLUSTRATIVE: Apple's 10-K discloses only total company CapEx and total D&A — not a retail-specific breakdown. This schedule models Retail CapEx as an estimated 15% slice of total company CapEx, split across three categories, and rolls a simplified straight-line depreciation schedule forward. Every blue input is an assumption, not a disclosed figure.
A4: ($ in millions unless noted) | B4: FY2024A | C4: FY2025A | D4: FY2026E | E4: FY2027E | F4: FY2028E
A6: NEW STORE BUILDOUTS
A7: New Stores Opened (#) | B7: n/d | C7: n/d | D7: 16 | E7: 17 | F7: 18
A8: Cost per New Store ($M) | B8: n/d | C8: n/d | D8: 12 | E8: 12.5 | F8: 13
A9: New Store Buildout CapEx | B9: 142 | C9: 191 | D9: =D7*D8 -> 192 | E9: =E7*E8 -> 212.5 | F9: =F7*F8 -> 234
A11: STORE REMODELS
A12: Stores Remodeled (#) | B12: n/d | C12: n/d | D12: 138 | E12: 142 | F12: 146
A13: Cost per Remodel ($M) | B13: n/d | C13: n/d | D13: 2.5 | E13: 2.6 | F13: 2.7
A14: Store Remodel CapEx | B14: 255 | C14: 343 | D14: =D12*D13 -> 345 | E14: =E12*E13 -> 369.2 | F14: =F12*F13 -> 394.2
A16: RETAIL IT
A17: Retail IT CapEx Growth %, YoY | B17: n/d | C17: n/d | D17: 0.08 | E17: 0.08 | F17: 0.07
A18: Retail IT CapEx | B18: 170 | C18: 229 | D18: =C18*(1+D17) -> 247.32 | E18: =D18*(1+E17) -> 267.1056 | F18: =E18*(1+F17) -> 285.80299
A20: TOTAL RETAIL CAPEX
A21: Total Retail CapEx | B21: =B9+B14+B18 -> 567 | C21: =C9+C14+C18 -> 763 | D21: =D9+D14+D18 -> 784.32 | E21: =E9+E14+E18 -> 848.8056 | F21: =F9+F14+F18 -> 914.00299
A22: Memo: Retail CapEx as % of Total Company CapEx | B22: =B21/9447 -> 0.060019054 | C22: =C21/12715 -> 0.060007865 | D22: =D21/(-Cash_Flow!D$20) -> 0.063848838 | E22: =E21/(-Cash_Flow!E$20) -> 0.065026432 | F22: =F21/(-Cash_Flow!F$20) -> 0.068588767
A24: DEPRECIATION SCHEDULE (simplified straight-line, half-year convention on new CapEx)
A25: New Store Buildouts — Useful Life (years) | D25: 15 | E25: =D25 -> 15 | F25: =E25 -> 15
A26: Store Remodels — Useful Life (years) | D26: 8 | E26: =D26 -> 8 | F26: =E26 -> 8
A27: Retail IT — Useful Life (years) | D27: 4 | E27: =D27 -> 4 | F27: =E27 -> 4
A29: Beginning Net Retail PP&E — New Store Buildouts | B29: 1800 | C29: =B29+B9-B32 -> 1817.2667 | D29: =C29+C9-C32 -> 1880.7489 | E29: =D29+D9-D32 -> 1940.9656 | F29: =E29+E9-E32 -> 2016.9846
A30: Beginning Net Retail PP&E — Store Remodels | B30: 700 | C30: =B30+B14-B32 -> 830.26667 | D30: =C30+C14-C32 -> 1045.7489 | E30: =D30+D14-D32 -> 1258.9656 | F30: =E30+E14-E32 -> 1491.6846
A31: Beginning Net Retail PP&E — Retail IT | B31: 500 | C31: =B31+B18-B32 -> 545.26667 | D31: =C31+C18-C32 -> 646.74889 | E31: =D31+D18-D32 -> 762.28563 | F31: =E31+E18-E32 -> 892.91019
A32: Depreciation — New Store Buildouts | B32: =B29/$D$25+(B9*0.5)/$D$25 -> 124.73333 | C32: =C29/$D$25+(C9*0.5)/$D$25 -> 127.51778 | D32: =D29/D25+(D9*0.5)/D25 -> 131.78326 | E32: =E29/E25+(E9*0.5)/E25 -> 136.48104 | F32: =F29/F25+(F9*0.5)/F25 -> 142.26564
A33: Depreciation — Store Remodels | B33: =B30/$D$26+(B14*0.5)/$D$26 -> 103.4375 | C33: =C30/$D$26+(C14*0.5)/$D$26 -> 125.22083 | D33: =D30/D26+(D14*0.5)/D26 -> 152.28111 | E33: =E30/E26+(E14*0.5)/E26 -> 180.4457 | F33: =F30/F26+(F14*0.5)/F26 -> 211.09807
A34: Depreciation — Retail IT | B34: =B31/$D$27+(B18*0.5)/$D$27 -> 146.25 | C34: =C31/$D$27+(C18*0.5)/$D$27 -> 164.94167 | D34: =D31/D27+(D18*0.5)/D27 -> 192.60222 | E34: =E31/E27+(E18*0.5)/E27 -> 223.95961 | F34: =F31/F27+(F18*0.5)/F27 -> 258.95292
A35: Total Retail Depreciation | B35: =B32+B33+B34 -> 374.42083 | C35: =C32+C33+C34 -> 417.68028 | D35: =D32+D33+D34 -> 476.66659 | E35: =E32+E33+E34 -> 540.88635 | F35: =F32+F33+F34 -> 612.31663

Sheet GRS_Headcount
A1: Apple Retail — GRS Headcount Schedule (Global Retail Support)
A2: ILLUSTRATIVE: Apple discloses only total company headcount (~166,000 FTE as of FY2025, per 10-K). GRS-specific headcount, contractor mix, and cost-per-head are not disclosed — this is a modeled corporate-support cost schedule of the type a Retail FP&A analyst maintains internally.
A4: ($ in millions unless noted; headcount in whole FTEs/contractors) | B4: FY2024A | C4: FY2025A | D4: FY2026E | E4: FY2027E | F4: FY2028E
A6: BASE CASE HEADCOUNT
A7: Corporate FTEs (GRS) | B7: 2750 | C7: 2900 | D7: 3050 | E7: 3150 | F7: 3250
A8: External Contractors (GRS) | B8: 820 | C8: 900 | D8: 950 | E8: 970 | F8: 980
A9: Total GRS Headcount | B9: =B7+B8 -> 3570 | C9: =C7+C8 -> 3800 | D9: =D7+D8 -> 4000 | E9: =E7+E8 -> 4120 | F9: =F7+F8 -> 4230
A10: Contractors as % of Total Headcount | B10: =B8/B9 -> 0.22969188 | C10: =C8/C9 -> 0.23684211 | D10: =D8/D9 -> 0.2375 | E10: =E8/E9 -> 0.23543689 | F10: =F8/F9 -> 0.23167849
A12: COST ASSUMPTIONS
A13: Average Fully-Loaded Cost per FTE ($K/year) | B13: 165 | C13: 172 | D13: 178 | E13: 183 | F13: 189
A14: Average Cost per Contractor ($K/year, bill rate basis) | B14: 195 | C14: 205 | D14: 210 | E14: 214 | F14: 218
A16: BASE CASE RUN RATE
A17: Total FTE Cost ($M) | B17: =B7*B13/1000 -> 453.75 | C17: =C7*C13/1000 -> 498.8 | D17: =D7*D13/1000 -> 542.9 | E17: =E7*E13/1000 -> 576.45 | F17: =F7*F13/1000 -> 614.25
A18: Total Contractor Cost ($M) | B18: =B8*B14/1000 -> 159.9 | C18: =C8*C14/1000 -> 184.5 | D18: =D8*D14/1000 -> 199.5 | E18: =E8*E14/1000 -> 207.58 | F18: =F8*F14/1000 -> 213.64
A19: Total GRS Annual Run Rate ($M) | B19: =B17+B18 -> 613.65 | C19: =C17+C18 -> 683.3 | D19: =D17+D18 -> 742.4 | E19: =E17+E18 -> 784.03 | F19: =F17+F18 -> 827.89
A20: Total GRS Monthly Run Rate ($M) | B20: =B19/12 -> 51.1375 | C20: =C19/12 -> 56.941667 | D20: =D19/12 -> 61.866667 | E20: =E19/12 -> 65.335833 | F20: =F19/12 -> 68.990833
A21: Memo: GRS Run Rate as % of Total SG&A | B21: =B19/Income_Statement!B$29 -> 0.023514197 | C21: =C19/Income_Statement!C$29 -> 0.024756349 | D21: =D19/Income_Statement!D$29 -> 0.025432034 | E21: =E19/Income_Statement!E$29 -> 0.025696562 | F21: =F19/Income_Statement!F$29 -> 0.02605533
A23: SCENARIO TOGGLE: CONVERT CONTRACTORS TO FTE
A24: Contractors Converted to FTE (#) | D24: 5 | E24: 5 | F24: 5
A25: Scenario: Corporate FTEs (post-conversion) | D25: =D7+D24 -> 3055 | E25: =E7+E24 -> 3155 | F25: =F7+F24 -> 3255
A26: Scenario: External Contractors (post-conversion) | D26: =D8-D24 -> 945 | E26: =E8-E24 -> 965 | F26: =F8-F24 -> 975
A27: Scenario: Total GRS Annual Run Rate ($M) | D27: =(D25*D13/1000)+(D26*D14/1000) -> 742.24 | E27: =(E25*E13/1000)+(E26*E14/1000) -> 783.875 | F27: =(F25*F13/1000)+(F26*F14/1000) -> 827.745
A28: Scenario Impact vs. Base Case ($M/year) | D28: =D27-D19 -> -0.16 | E28: =E27-E19 -> -0.155 | F28: =F27-F19 -> -0.145
